structlib/__init__.py
structlib/byteorder.py
structlib/errors.py
structlib/typing_.py
structlib/utils.py
structlib/abc_/__init__.py
structlib/abc_/packing.py
structlib/abc_/typedef.py
structlib/io/__init__.py
structlib/io/bufferio.py
structlib/io/streamio.py
structlib/protocols/__init__.py
structlib/protocols/packing.py
structlib/protocols/typedef.py
structlib/typedefs/__init__.py
structlib/typedefs/array.py
structlib/typedefs/boolean.py
structlib/typedefs/datastruct.py
structlib/typedefs/floating.py
structlib/typedefs/integer.py
structlib/typedefs/strings.py
structlib/typedefs/structure.py
structlib/typedefs/varlen.py
obj_struct_lib-2022.1b2.dist-info/LICENSE
obj_struct_lib-2022.1b2.dist-info/METADATA
obj_struct_lib-2022.1b2.dist-info/WHEEL
obj_struct_lib-2022.1b2.dist-info/top_level.txt
obj_struct_lib-2022.1b2.dist-info/RECORD
