Metadata-Version: 2.1
Name: obj-struct-lib
Version: 2022.1b2
Summary: An object-oriented alternative to the built-in struct module.
Home-page: https://github.com/ModernMAK/Object-Struct-Library
Author: Marcus Kertesz
Project-URL: Bug Tracker, https://github.com/ModernMAK/Object-Struct-Library/issues
Classifier: Programming Language :: Python :: 3 :: Only
Classifier: Programming Language :: Python :: 3.9
Classifier: Programming Language :: Python :: 3.10
Classifier: License :: OSI Approved :: MIT License
Classifier: Operating System :: OS Independent
Classifier: Topic :: Software Development :: Libraries
Requires-Python: >=3.9
License-File: LICENSE
